odoo8_addon_crm_lead_firstname-8.0.1.0.0.99.dev21-py3.8-nspkg.pth
odoo_addons/crm_lead_firstname/README.rst
odoo_addons/crm_lead_firstname/__init__.py
odoo_addons/crm_lead_firstname/__openerp__.py
odoo_addons/crm_lead_firstname/i18n/bg.po
odoo_addons/crm_lead_firstname/i18n/crm_lead_firstname.pot
odoo_addons/crm_lead_firstname/i18n/de.po
odoo_addons/crm_lead_firstname/i18n/es.po
odoo_addons/crm_lead_firstname/i18n/fr.po
odoo_addons/crm_lead_firstname/i18n/fr_CH.po
odoo_addons/crm_lead_firstname/i18n/hr.po
odoo_addons/crm_lead_firstname/i18n/it.po
odoo_addons/crm_lead_firstname/i18n/pt_BR.po
odoo_addons/crm_lead_firstname/i18n/sk.po
odoo_addons/crm_lead_firstname/i18n/sl.po
odoo_addons/crm_lead_firstname/i18n/tr.po
odoo_addons/crm_lead_firstname/i18n/zh_CN.po
odoo_addons/crm_lead_firstname/models/__init__.py
odoo_addons/crm_lead_firstname/models/crm_lead.py
odoo_addons/crm_lead_firstname/static/description/icon.png
odoo_addons/crm_lead_firstname/tests/__init__.py
odoo_addons/crm_lead_firstname/tests/test_crm_lead.py
odoo_addons/crm_lead_firstname/views/crm_lead_view.xml
odoo8_addon_crm_lead_firstname-8.0.1.0.0.99.dev21.dist-info/METADATA
odoo8_addon_crm_lead_firstname-8.0.1.0.0.99.dev21.dist-info/WHEEL
odoo8_addon_crm_lead_firstname-8.0.1.0.0.99.dev21.dist-info/namespace_packages.txt
odoo8_addon_crm_lead_firstname-8.0.1.0.0.99.dev21.dist-info/top_level.txt
odoo8_addon_crm_lead_firstname-8.0.1.0.0.99.dev21.dist-info/RECORD
